nonebot_plugin_ddtv_webhook/__init__.py
nonebot_plugin_ddtv_webhook/config.py
nonebot_plugin_ddtv_webhook-0.1.0.dist-info/LICENSE
nonebot_plugin_ddtv_webhook-0.1.0.dist-info/METADATA
nonebot_plugin_ddtv_webhook-0.1.0.dist-info/WHEEL
nonebot_plugin_ddtv_webhook-0.1.0.dist-info/RECORD
