Metadata-Version: 2.3
Name: nonebot-plugin-ddtv-webhook
Version: 0.1.0
Summary: 处理DDTV WebHook并推送相关信息
License: MIT
Keywords: nonebot2,ddtv,webhook
Author: EffectW
Requires-Python: <4.0,>=3.10
Classifier: Programming Language :: Python :: 3
Classifier: License :: OSI Approved :: MIT License
Classifier: Operating System :: OS Independent
Requires-Dist: nonebot-adapter-onebot (>=2.2.2,<3.0.0)
Requires-Dist: nonebot2 (>=2.0.0,<3.0.0)
Project-URL: Documentation, https://github.com/Effect-Wei/nonebot-plugin-ddtv-webhook#readme
Project-URL: Homepage, https://github.com/Effect-Wei/nonebot-plugin-ddtv-webhook
Project-URL: Repository, https://github.com/Effect-Wei/nonebot-plugin-ddtv-webhook
